tenop/__init__.py
tenop/buffers.py
tenop/device.py
tenop/dtypes.py
tenop/helpers.py
tenop/shape.py
tenop/tensor.py
tenop/vm.py
tenop/engine/__init__.py
tenop/engine/cpu.pyi
tenop/engine/cpu.so
tenop/engine/cuda.pyi
tenop/engine/cuda.so
tenop-0.0.2.dist-info/LICENSE
tenop-0.0.2.dist-info/METADATA
tenop-0.0.2.dist-info/WHEEL
tenop-0.0.2.dist-info/top_level.txt
tenop-0.0.2.dist-info/RECORD
