Metadata-Version: 2.1
Name: tenop
Version: 0.0.2
Summary: A lightweight & minimalist tensor computation library with CUDA backend
Home-page: https://github.com/0xhilSa/tenop
Author: Sahil Rajwar
License: MIT
Platform: UNKNOWN
Classifier: Programming Language :: Python :: 3
Classifier: Operating System :: POSIX :: Linux
Requires-Python: >=3.10
License-File: LICENSE
Requires-Dist: numpy
